LICENSE
MANIFEST.in
README.md
setup.py
accounts/__init__.py
accounts/admin.py
accounts/apps.py
accounts/models.py
accounts/tests.py
accounts/migrations/0001_initial.py
accounts/migrations/__init__.py
mini_django_accounts.egg-info/PKG-INFO
mini_django_accounts.egg-info/SOURCES.txt
mini_django_accounts.egg-info/dependency_links.txt
mini_django_accounts.egg-info/requires.txt
mini_django_accounts.egg-info/top_level.txt
tests/__init__.py
tests/test_settings.py